google_takeout_email.py
google_takeout_email-0.0.5.dist-info/LICENSE
google_takeout_email-0.0.5.dist-info/WHEEL
google_takeout_email-0.0.5.dist-info/METADATA
google_takeout_email-0.0.5.dist-info/RECORD
