Metadata-Version: 2.1
Name: google_takeout_email
Version: 0.0.5
Summary: Contains a reader for mailbox files, MailboxReader, and utility functions for parsing email addresses.
Author-email: Jarno Rantaharju <jarno.rantaharju@aalto.fi>
Classifier: License :: OSI Approved :: MIT License
Requires-Dist: chardet
Requires-Dist: pytest ; extra == "test"
Project-URL: Repository, https://github.com/rantahar/google_takeout_email
Provides-Extra: test
